chinese_year_calc-0.1.1.dist-info/licenses/LICENSE
chyear/__init__.py
chyear/__main__.py
chinese_year_calc-0.1.1.dist-info/METADATA
chinese_year_calc-0.1.1.dist-info/WHEEL
chinese_year_calc-0.1.1.dist-info/entry_points.txt
chinese_year_calc-0.1.1.dist-info/top_level.txt
chinese_year_calc-0.1.1.dist-info/RECORD
