Metadata-Version: 2.4
Name: chinese_year_calc
Version: 0.1.1
Summary: 中国纪年计算器
Home-page: https://github.com/xystudio889/chinese-year-calc
Author: xystudio
Author-email: 173288240@qq.com
License: MIT
Classifier: Programming Language :: Python :: 3
Classifier: License :: OSI Approved :: MIT License
Classifier: Operating System :: OS Independent
Requires-Python: >=3.6
License-File: LICENSE
Dynamic: author
Dynamic: author-email
Dynamic: classifier
Dynamic: description
Dynamic: description-content-type
Dynamic: home-page
Dynamic: keywords
Dynamic: license
Dynamic: license-file
Dynamic: requires-python
Dynamic: summary
